python_awair_local_sensors/__init__.py
python_awair_local_sensors/air_data.py
python_awair_local_sensors/attrdict.py
python_awair_local_sensors/auth.py
python_awair_local_sensors/client.py
python_awair_local_sensors/const.py
python_awair_local_sensors/devices.py
python_awair_local_sensors/exceptions.py
python_awair_local_sensors/indices.py
python_awair_local_sensors/sensors.py
python_awair_local_sensors/user.py
python_awair_local_sensors-0.2.1.dist-info/LICENSE
python_awair_local_sensors-0.2.1.dist-info/WHEEL
python_awair_local_sensors-0.2.1.dist-info/METADATA
python_awair_local_sensors-0.2.1.dist-info/RECORD
