Metadata-Version: 2.1
Name: python-awair-local-sensors
Version: 0.2.1
Summary: asyncio client for the Awair GraphQL API
Home-page: https://github.com/bpowers/python_awair
License: MIT
Keywords: awair,getawair,api,async,asyncio
Author: Andrew Hayworth
Author-email: ahayworth@gmail.com
Requires-Python: >=3.6,<4.0
Classifier: Development Status :: 4 - Beta
Classifier: Framework :: AsyncIO
Classifier: Intended Audience :: Developers
Classifier: License :: OSI Approved :: MIT License
Classifier: Programming Language :: Python :: 3
Classifier: Programming Language :: Python :: 3.6
Classifier: Programming Language :: Python :: 3.7
Classifier: Programming Language :: Python :: 3.8
Classifier: Topic :: Home Automation
Classifier: Topic :: Software Development :: Libraries
Classifier: Typing :: Typed
Requires-Dist: aiohttp (>=3.6.2,<4.0.0)
Requires-Dist: voluptuous (>=0.11.7,<0.12.0)
Project-URL: Repository, https://github.com/bpowers/python_awair
Project-URL: Say Thanks, https://saythanks.io/to/ahayworth@gmail.com
